delta_hybrid_scd/__init__.py
delta_hybrid_scd/scd_handler.py
delta_hybrid_scd-0.1.3.dist-info/METADATA
delta_hybrid_scd-0.1.3.dist-info/WHEEL
delta_hybrid_scd-0.1.3.dist-info/RECORD
