Metadata-Version: 2.3
Name: delta-hybrid-scd
Version: 0.1.3
Summary: A package for implementing hybrid SCD1 and SCD2 operations using Delta Tables in Databricks
Author: Prateek Mishra
Requires-Python: >=3.8
Classifier: Programming Language :: Python :: 3
Classifier: Programming Language :: Python :: 3.8
Classifier: Programming Language :: Python :: 3.9
Classifier: Programming Language :: Python :: 3.10
Classifier: Programming Language :: Python :: 3.11
Classifier: Programming Language :: Python :: 3.12
Classifier: Programming Language :: Python :: 3.13
Requires-Dist: databricks-api (>=0.9.0,<0.10.0)
Requires-Dist: datetime (>=5.5,<6.0)
Requires-Dist: delta-spark (>=3.3.1,<4.0.0)
Requires-Dist: pyspark (>=3.5.5,<4.0.0)
